{
  "products": [
    {
      "id": "1",
      "productName": "mobile",
      "price": 5999,
      "inTheBox":
        "Handset, Battery, Charger, User Manual, Headset, Screen Guard",
      "modelNumber": "ERA-2V",
      "size": "5 inch",
      "brand": "Lenova",
      "color": "white",
      "touchScreen": "yes",
      "image": "http://localhost:4000/images/mobile.jpeg"
    },
    {
      "id": "2",
      "productName": "Air conditioner",
      "price": 23999,
      "inTheBox":
        "1 Indoor Unit 1 Outdoor Unit Remote Control 2 Batteries Connecting Pipes User Manual Warranty Card",
      "modelNumber": "ERA-2V",
      "size": "5 inch",
      "brand": "Carrier",
      "color": "white",
      "touchScreen": "yes",
      "image": "http://localhost:4000/images/air.jpeg"
    },
    {
      "id": "3",
      "productName": "Mobile",
      "price": 13999,
      "inTheBox": "Handset, Charger, Type C USB Cable,White Earphone",
      "modelNumber": "XT1663-2V",
      "size": "5.5 inch",
      "brand": "Gold",
      "color": "Black",
      "touchScreen": "yes",
      "image": "http://localhost:4000/images/mobile.jpeg"
    },
    {
      "id": "4",
      "productName": "Home theatre",
      "price": 13999,
      "inTheBox": "unit box,remote,USB Cable,One Tower Speaker, Manual",
      "modelNumber": "XT163-2V",
      "size": "22.5 inch",
      "brand": "Sony",
      "color": "Black",
      "touchScreen": "No"
    },
    {
      "id": "5",
      "productName": "Laptop",
      "price": 43999,
      "inTheBox": "MONITOR, Power cable Power Adapter Speaker HDMI cable",
      "modelNumber": "A A1466-2V",
      "size": "22.5 inch",
      "brand": "Dell",
      "color": "Black",
      "touchScreen": "Yes",
      "image": "http://localhost:4000/images/apple-lap.jpeg"
    },
    {
      "id": "6",
      "productName": "MacBook",
      "price": 113999,
      "inTheBox":
        "Laptop, Battery, Power Adaptor, User Guide, Warranty Documents",
      "modelNumber": "MQD32HN/A A1466",
      "size": "15.5 inch",
      "brand": "Apple",
      "color": "silver",
      "touchScreen": "Yes",
      "image": "http://localhost:4000/images/apple-lap.jpeg"
    },
    {
      "id": "7",
      "productName": "MacBook",
      "price": 113999,
      "inTheBox":
        "Laptop, Battery, Power Adaptor, User Guide, Warranty Documents",
      "modelNumber": "MQD32HN/A A1466",
      "size": "15.5 inch",
      "brand": "Apple",
      "color": "White",
      "touchScreen": "Yes",
      "image": "http://localhost:4000/images/apple-lap.jpeg"
    },
    {
      "id": "8",
      "productName": "washing machine",
      "price": 113999,
      "inTheBox":
        "User Manual Outlet Pipe 1 Washing Machine Inlet Pipe Lint Filter Rat Mesh",
      "modelNumber": "MQD466",
      "size": "6 kg",
      "brand": "Haier",
      "color": "Silver",
      "touchScreen": "Yes",
      "image": "http://localhost:4000/images/washing.jpeg"
    },
    {
      "id": "9",
      "productName": "Printer",
      "price": 10999,
      "inTheBox":
        "Laptop, Battery, Power Adaptor, User Guide, Warranty Documents",
      "modelNumber": "MQD466",
      "size": "6 kg",
      "brand": "Haier",
      "color": "Silver",
      "touchScreen": "Yes",
      "image": "http://localhost:4000/images/printer.jpeg"
    },
    {
      "id": "10",
      "productName": "Camera",
      "price": 99999,
      "inTheBox":
        "EN-EL14a rechargeable Li-ion battery (with terminal cover), MH-24 battery charger (plug adapter supplied in countries or regions where required; shape depends on country of sale), DK-25 rubber eyecup, BF-1B body cap, AN-DC3 strap",
      "size": "23.5 x 15.6 mm",
      "brand": "Nikon",
      "color": "Black",
      "touchScreen": "Yes",
      "image": "http://localhost:4000/images/camera.jpeg"
    },
    {
      "id": "11",
      "productName": "Memory Card",
      "price": 679,
      "inTheBox": "menory card,Manual",
      "size": "128 GB",
      "brand": "SanDisk",
      "color": "Black",
      "touchScreen": "No",
      "image": "http://localhost:4000/images/memory-card.jpeg"
    },
    {
      "id": "12",
      "productName": "Laptop",
      "price": 55999,
      "inTheBox": "MONITOR, Power cable Power Adapter Speaker HDMI cable",
      "size": "13.3 inch",
      "brand": "Thoshiba",
      "color": "Black",
      "touchScreen": "Yes",
      "image": "http://localhost:4000/images/dell-lap.jpeg"
    },
    {
      "id": "13",
      "productName": "MacBook",
      "price": 125349,
      "inTheBox":
        "Laptop, Battery, Power Adaptor, User Guide, Warranty Documents",
      "size": "13.3 inch",
      "brand": "Apple",
      "color": "Gold",
      "touchScreen": "Yes",
      "image": "http://localhost:4000/images/apple-lap.jpeg"
    },
    {
      "id": "14",
      "productName": "Power-bank",
      "price": 11049,
      "inTheBox":
        "Laptop, Battery, Power Adaptor, User Guide, Warranty Documents",
      "size": "3inches",
      "brand": "Intex",
      "color": "gray",
      "touchScreen": "Yes",
      "image": "http://localhost:4000/images/power-bank.jpeg"
    },
    {
      "id": "15",
      "productName": "Wrist-Watch",
      "price": 1789,
      "inTheBox":
        "Laptop, Battery, Power Adaptor, User Guide, Warranty Documents",
      "size": "4inches",
      "brand": "samsung",
      "color": "lightgray",
      "touchScreen": "No",
      "image": "http://localhost:4000/images/watch1.jpeg"
    },
    {
      "id": "16",
      "productName": "Air conditioner",
      "price": 122789,
      "inTheBox":
        "1 Indoor Unit 1 Outdoor Unit Remote Control 2 Batteries Connecting Pipes User Manual Warranty Card Power Adaptor, User Guide, Warranty Documents",
      "size": "70 inches",
      "brand": "sony",
      "color": "lightgray",
      "touchScreen": "No",
      "image": "http://localhost:4000/images/air.jpeg"
    },
    {
      "id": "17",
      "productName": "Mobile",
      "price": 5785,
      "inTheBox":
        "Handset, Charger, Type C USB Cable,White Earphone, User Manual Warranty Card Power Adaptor, User Guide",
      "size": "5.1cm",
      "brand": "sony",
      "color": "gold",
      "touchScreen": "Yes",
      "image": "http://localhost:4000/images/mobile.jpeg"
    },
    {
      "id": "18",
      "productName": "Mobile",
      "price": 11458,
      "inTheBox":
        "Handset, Lightening Charger, Quick Start Guide, Data Cable, Headphone",
      "size": "5.5cm",
      "brand": "redmi",
      "color": "silver",
      "touchScreen": "Yes",
      "image": "http://localhost:4000/images/mobile.jpeg"
    },
    {
      "id": "19",
      "productName": "mouse",
      "price": 1458,
      "inTheBox": "mouse, Data Cable,USB",
      "size": "15.5cm",
      "brand": "samsung",
      "color": "black",
      "touchScreen": "No",
      "image": "http://localhost:4000/images/mouse.jpeg"
    },
    {
      "id": "19",
      "productName": "CPU",
      "price": 12435,
      "inTheBox": "CPU unit,data Cable,user Manual",
      "size": "15.5cm",
      "brand": "HP",
      "color": "black",
      "touchScreen": "No"
    }
  ],
  "users": []
}
